README.rst
setup.py
HZ_Redis_Global.egg-info/PKG-INFO
HZ_Redis_Global.egg-info/SOURCES.txt
HZ_Redis_Global.egg-info/dependency_links.txt
HZ_Redis_Global.egg-info/top_level.txt
ari_redis/VirtualSlot.py
ari_redis/__init__.py
ari_redis/globalredis.py