Metadata-Version: 1.0
Name: HZ-Redis-Global
Version: 0.1
Summary: 致敬蘑菇先生为华住写的C#版本的虚拟桶分片法缩写的python版本
Home-page: http://www.cnblogs.com/mushroom/p/4542772.html
Author: luyun001
Author-email: luyun001@huazhu.com
License: MIT
Platform: UNKNOWN
